README.md
setup.py
computer_vision_marking_aicore.egg-info/PKG-INFO
computer_vision_marking_aicore.egg-info/SOURCES.txt
computer_vision_marking_aicore.egg-info/dependency_links.txt
computer_vision_marking_aicore.egg-info/requires.txt
computer_vision_marking_aicore.egg-info/top_level.txt
computer_vision_test/__init__.py
computer_vision_test/test_milestone1.py
computer_vision_test/test_milestone2.py
computer_vision_test/test_milestone3.py
computer_vision_test/test_milestone4_p1.py
computer_vision_test/test_milestone4_p2.py
computer_vision_test/test_milestone5_p1.py
computer_vision_test/test_milestone5_p2.py
computer_vision_test/verify.py
computer_vision_test/verify_milestone1.py
computer_vision_test/verify_milestone2.py
computer_vision_test/verify_milestone3.py
computer_vision_test/verify_milestone4_p1.py
computer_vision_test/verify_milestone4_p2.py
computer_vision_test/verify_milestone5_p1.py
computer_vision_test/verify_milestone5_p2.py