Metadata-Version: 2.1
Name: computer-vision-marking-aicore
Version: 1.1.10
Summary: An automated marking system for the computer vision scenario
Author: Ivan Ying
Author-email: ivan@theaicore.com
Requires-Python: >=3.6
